odoo/addons/l10n_it_vat_payability/README.rst
odoo/addons/l10n_it_vat_payability/__init__.py
odoo/addons/l10n_it_vat_payability/__manifest__.py
odoo/addons/l10n_it_vat_payability/i18n/es_AR.po
odoo/addons/l10n_it_vat_payability/i18n/it.po
odoo/addons/l10n_it_vat_payability/i18n/l10n_it_vat_payability.pot
odoo/addons/l10n_it_vat_payability/models/__init__.py
odoo/addons/l10n_it_vat_payability/models/account_tax.py
odoo/addons/l10n_it_vat_payability/readme/CONTRIBUTORS.md
odoo/addons/l10n_it_vat_payability/readme/DESCRIPTION.md
odoo/addons/l10n_it_vat_payability/static/description/icon.png
odoo/addons/l10n_it_vat_payability/static/description/index.html
odoo/addons/l10n_it_vat_payability/views/account_view.xml
odoo_addon_l10n_it_vat_payability-16.0.1.0.0.7.dist-info/METADATA
odoo_addon_l10n_it_vat_payability-16.0.1.0.0.7.dist-info/WHEEL
odoo_addon_l10n_it_vat_payability-16.0.1.0.0.7.dist-info/top_level.txt
odoo_addon_l10n_it_vat_payability-16.0.1.0.0.7.dist-info/RECORD
