Metadata-Version: 2.1
Name: odoo-addon-l10n_it_vat_payability
Version: 16.0.1.0.0.7
Requires-Python: >=3.10
Requires-Dist: odoo>=16.0a,<16.1dev
Summary: =?utf-8?q?ITA_-_Esigibilit=C3=A0_IVA?=
Home-page: https://github.com/OCA/l10n-italy
License: LGPL-3
Author: Openforce di Camilli Alessandro, Odoo Community Association (OCA)
Author-email: support@odoo-community.org
Classifier: Programming Language :: Python
Classifier: Framework :: Odoo
Classifier: Framework :: Odoo :: 16.0
Classifier: License :: OSI Approved :: GNU Lesser General Public License v3 (LGPLv3)
Classifier: Development Status :: 4 - Beta
